LICENSE
MANIFEST.in
README.md
requirements.txt
setup.cfg
setup.py
django_mp_shop_orders.egg-info/PKG-INFO
django_mp_shop_orders.egg-info/SOURCES.txt
django_mp_shop_orders.egg-info/dependency_links.txt
django_mp_shop_orders.egg-info/top_level.txt
orders/__init__.py
orders/admin.py
orders/apps.py
orders/constants.py
orders/decorators.py
orders/utils.py
orders/locale/ru/LC_MESSAGES/django.mo
orders/locale/ru/LC_MESSAGES/django.po
orders/locale/uk/LC_MESSAGES/django.mo
orders/locale/uk/LC_MESSAGES/django.po
orders/models/__init__.py
orders/models/delivery_method.py
orders/models/order.py
orders/models/order_item.py
orders/models/order_status.py
orders/models/payment_method.py
orders/templates/orders/new_order_email_for_manager.html
orders/templates/orders/new_order_message.html
orders/templates/orders/new_order_sms_for_manager.txt
orders/templates/orders/admin/customer.html
orders/templates/orders/admin/delivery.html
orders/templates/orders/admin/products.html